ryumem/__init__.py
ryumem/main.py
ryumem/core/__init__.py
ryumem/core/config.py
ryumem/core/metadata_models.py
ryumem/core/models.py
ryumem/integrations/__init__.py
ryumem/integrations/google_adk.py
ryumem/integrations/tool_tracker.py
ryumem-0.6.1.dist-info/licenses/LICENSE
ryumem-0.6.1.dist-info/METADATA
ryumem-0.6.1.dist-info/WHEEL
ryumem-0.6.1.dist-info/top_level.txt
ryumem-0.6.1.dist-info/RECORD
