Metadata-Version: 2.4
Name: ryumem
Version: 0.6.1
Summary: Bi-temporal knowledge graph memory system using ryugraph
Author: Ryumem Team
License: AGPL-3.0-only
Project-URL: Homepage, https://github.com/predictable-labs/ryumem
Project-URL: Repository, https://github.com/predictable-labs/ryumem
Project-URL: Bug Tracker, https://github.com/predictable-labs/ryumem/issues
Project-URL: Documentation, https://github.com/predictable-labs/ryumem#readme
Keywords: knowledge graph,memory,rag,llm,temporal,graph database
Classifier: Development Status :: 3 - Alpha
Classifier: Intended Audience :: Developers
Classifier: License :: OSI Approved :: GNU Affero General Public License v3
Classifier: Programming Language :: Python :: 3
Classifier: Programming Language :: Python :: 3.10
Classifier: Programming Language :: Python :: 3.11
Classifier: Programming Language :: Python :: 3.12
Requires-Python: >=3.10
License-File: LICENSE
Requires-Dist: ryugraph>=25.9.2
Requires-Dist: openai>=1.0.0
Requires-Dist: litellm>=1.0.0
Requires-Dist: pydantic>=2.0.0
Requires-Dist: pydantic-settings>=2.0.0
Requires-Dist: numpy>=1.24.0
Requires-Dist: python-dotenv>=1.0.0
Requires-Dist: networkx>=3.0
Requires-Dist: scipy>=1.10.0
Requires-Dist: tenacity>=8.0.0
Requires-Dist: rank-bm25>=0.2.2
Requires-Dist: requests>=2.31.0
Requires-Dist: google-genai>=0.2.0
Provides-Extra: dev
Requires-Dist: pytest>=7.4.0; extra == "dev"
Requires-Dist: pytest-asyncio>=0.21.0; extra == "dev"
Requires-Dist: pytest-cov>=4.1.0; extra == "dev"
Requires-Dist: black>=23.0.0; extra == "dev"
Requires-Dist: ruff>=0.1.0; extra == "dev"
Requires-Dist: mypy>=1.5.0; extra == "dev"
Provides-Extra: google-adk
Requires-Dist: google-adk>=1.18.0; extra == "google-adk"
Dynamic: license-file
